batchcreate/__init__.py
batchcreate/batchcreator.py
batchcreate-0.1.5.dist-info/METADATA
batchcreate-0.1.5.dist-info/WHEEL
batchcreate-0.1.5.dist-info/top_level.txt
batchcreate-0.1.5.dist-info/RECORD
