Metadata-Version: 2.1
Name: batchcreate
Version: 0.1.5
Summary: Demo batchcreate library
Home-page: https://batchcreate.readthedocs.io/
Author: Amruta K
Author-email: 
License: UNKNOWN
Platform: UNKNOWN
